[
    {
        "%vlocity_namespace%__FloorPrice__c": "",
        "%vlocity_namespace%__OverageCharge__c": "",
        "%vlocity_namespace%__OverageUOM__c": "",
        "%vlocity_namespace%__RecurringPrice__c": "",
        "%vlocity_namespace%__RecurringUOM__c": "Monthly",
        "IsActive": true,
        "IsArchived": false,
        "Name": "Hospital Based Services",
        "Pricebook2.Name": "Standard Price Book",
        "Pricebook2Id": {
            "Name": "Standard Price Book",
            "VlocityDataPackType": "VlocityLookupMatchingKeyObject",
            "VlocityLookupRecordSourceKey": "Pricebook2/Standard Price Book",
            "VlocityRecordSObjectType": "Pricebook2"
        },
        "Product2.%vlocity_namespace%__GlobalKey__c": "6570c9b8-9770-4fd2-16dd-c1cc1335bcb7",
        "Product2Id": {
            "%vlocity_namespace%__GlobalKey__c": "6570c9b8-9770-4fd2-16dd-c1cc1335bcb7",
            "VlocityDataPackType": "VlocityMatchingKeyObject",
            "VlocityMatchingRecordSourceKey": "Product2/6570c9b8-9770-4fd2-16dd-c1cc1335bcb7",
            "VlocityRecordSObjectType": "Product2"
        },
        "ProductCode": "MA_Hosp_Based_Serv",
        "UnitPrice": 0,
        "UseStandardPrice": false,
        "VlocityDataPackType": "SObject",
        "VlocityRecordSObjectType": "PricebookEntry",
        "VlocityRecordSourceKey": "PricebookEntry/Pricebook2/Standard Price Book/Product2/6570c9b8-9770-4fd2-16dd-c1cc1335bcb7"
    }
]